[
  { "label": "護照", "category": "證件" },
  { "label": "護照影本", "category": "證件" },
  { "label": "飯店訂房確認信", "category": "證件" },
  { "label": "景點門票（Skytree、Shibuya Sky）", "category": "證件" },
  { "label": "來回機票", "category": "證件" },
  { "label": "牙刷", "category": "盥洗" },
  { "label": "牙膏", "category": "盥洗" },
  { "label": "防曬乳", "category": "盥洗" },
  { "label": "刮鬍刀", "category": "盥洗" },
  { "label": "手機充電器", "category": "電子" },
  { "label": "行動電源", "category": "電子" },
  { "label": "耳機", "category": "電子" },
  { "label": "相機", "category": "電子" },
  { "label": "萬用轉接頭（日本 A 型，同台灣）", "category": "電子" },
  { "label": "止痛藥", "category": "醫療" },
  { "label": "腸胃藥", "category": "醫療" },
  { "label": "日幣現金 ¥50,000-80,000", "category": "財務" },
  { "label": "信用卡", "category": "財務" },
  { "label": "Suica / PASMO 交通卡", "category": "財務" },
  { "label": "摺疊傘", "category": "其他" },
  { "label": "摺疊行李袋（裝公仔/電器戰利品）", "category": "其他" },
  { "label": "環保購物袋", "category": "其他" },
  { "label": "小毛巾（擦汗用）", "category": "其他" }
]
